setup.py
yearonequant/__init__.py
yearonequant/event.py
yearonequant/event_object.py
yearonequant/factor.py
yearonequant/util_quant.py
yearonequant.egg-info/PKG-INFO
yearonequant.egg-info/SOURCES.txt
yearonequant.egg-info/dependency_links.txt
yearonequant.egg-info/not-zip-safe
yearonequant.egg-info/requires.txt
yearonequant.egg-info/top_level.txt