Metadata-Version: 1.0
Name: yearonequant
Version: 1.5.6
Summary: Think as quant, trade as quant
Home-page: http://github.com/hyqLeonardo/yearonequant
Author: Leonardo
Author-email: hyq335335@163.com
License: MIT
Platform: UNKNOWN
